pmxbot/bookmarklet-min.js
pmxbot/bookmarklet.js
pmxbot/webhooks.py
pmxbot/compat/py311.py
pmxbot.webhooks-1.6.0.dist-info/LICENSE
pmxbot.webhooks-1.6.0.dist-info/METADATA
pmxbot.webhooks-1.6.0.dist-info/WHEEL
pmxbot.webhooks-1.6.0.dist-info/entry_points.txt
pmxbot.webhooks-1.6.0.dist-info/top_level.txt
pmxbot.webhooks-1.6.0.dist-info/RECORD
