Metadata-Version: 2.1
Name: pmxbot.webhooks
Version: 1.6.0
Summary: An HTTP-based webhook service for pmxbot
Home-page: https://github.com/jaraco/pmxbot.webhooks
Author: Jason R. Coombs
Author-email: jaraco@jaraco.com
Classifier: Development Status :: 5 - Production/Stable
Classifier: Intended Audience :: Developers
Classifier: License :: OSI Approved :: MIT License
Classifier: Programming Language :: Python :: 3
Classifier: Programming Language :: Python :: 3 :: Only
Requires-Python: >=3.8
License-File: LICENSE
Requires-Dist: twilio >=6
Requires-Dist: cherrypy-cors
Requires-Dist: more-itertools
Requires-Dist: importlib-resources ; python_version < "3.12"
Provides-Extra: docs
Requires-Dist: sphinx >=3.5 ; extra == 'docs'
Requires-Dist: jaraco.packaging >=9.3 ; extra == 'docs'
Requires-Dist: rst.linker >=1.9 ; extra == 'docs'
Requires-Dist: furo ; extra == 'docs'
Requires-Dist: sphinx-lint ; extra == 'docs'
Provides-Extra: testing
Requires-Dist: pytest !=8.1.1,>=6 ; extra == 'testing'
Requires-Dist: pytest-checkdocs >=2.4 ; extra == 'testing'
Requires-Dist: pytest-cov ; extra == 'testing'
Requires-Dist: pytest-mypy ; extra == 'testing'
Requires-Dist: pytest-enabler >=2.2 ; extra == 'testing'
Requires-Dist: pytest-ruff >=0.2.1 ; extra == 'testing'
Requires-Dist: pmxbot ; extra == 'testing'
